sdd_segmentation/__init__.py
sdd_segmentation/sdd.py
sdd_segmentation-0.1.0a2.dist-info/LICENSE
sdd_segmentation-0.1.0a2.dist-info/WHEEL
sdd_segmentation-0.1.0a2.dist-info/METADATA
sdd_segmentation-0.1.0a2.dist-info/RECORD
