Metadata-Version: 2.1
Name: sdd-segmentation
Version: 0.1.0a2
Summary: The python implementation of algorithm proposed by Z. Wang, 'A New Approach for Segmentation and Quantification of Cells or Nanoparticles,' in IEEE Transactions on Industrial Informatics, vol. 12, no. 3, pp. 962-971, June 2016, DOI: 10.1109/TII.2016.
Home-page: https://gitlab.com/digiratory/sdd-segmentation
License: BSD-3-Clause
Author: Aleksandr Sinitca
Author-email: siniza.s.94@gmail.com
Requires-Python: >=3.8,<4.0
Classifier: License :: OSI Approved :: BSD License
Classifier: Programming Language :: Python :: 3
Classifier: Programming Language :: Python :: 3.8
Requires-Dist: numpy (>=1.19.0,<2.0.0)
Requires-Dist: scipy (>=1.7.0,<2.0.0)
Project-URL: Repository, https://gitlab.com/digiratory/sdd-segmentation
